{
  "pianos": [
    {
      "model": "EC 109",
      "brand": "Young Chang",
      "photo": "/pianos/piano-exemple-1.jpg",
      "alt": "Photo du",
      "year": 1986,
      "color": "Noir laqué",
      "price": 1900,
      "manufacturing": "Coréenne",
      "size": "H109xL135xP50",
      "description": ""
    },
    {
      "model": "U-118",
      "brand": "Young Chang",
      "photo": "/pianos/piano-exemple-1.jpg",
      "alt": "Photo du",
      "year": 1986,
      "color": "Acajou",
      "price": 2400,
      "manufacturing": "Coréenne",
      "size": "H118xL145xP57",
      "description": ""
    },
    {
      "model": "Chippendale 108",
      "brand": "Schimmel",
      "photo": "/pianos/piano-exemple-1.jpg",
      "alt": "Photo du",
      "year": 1975,
      "color": "Rose fluo",
      "price": 3800,
      "manufacturing": "Allemande",
      "size": "H108xL145xP54",
      "description": "Mécanique Renner"
    }
  ]
}
